setup.py
django_lamson/__init__.py
django_lamson/models.py
django_lamson/tests.py
django_lamson/views.py
django_lamson.egg-info/PKG-INFO
django_lamson.egg-info/SOURCES.txt
django_lamson.egg-info/dependency_links.txt
django_lamson.egg-info/not-zip-safe
django_lamson.egg-info/requires.txt
django_lamson.egg-info/top_level.txt
django_lamson/management/__init__.py
django_lamson/management/commands/__init__.py
django_lamson/management/commands/lamson_log.py
django_lamson/management/commands/lamson_start.py
django_lamson/management/commands/lamson_stop.py
testproject/mailstore/__init__.py
testproject/mailstore/handlers.py
testproject/mailstore/models.py
testproject/mailstore/tests.py
testproject/mailstore/views.py