Metadata-Version: 1.0
Name: django-lamson
Version: 0.1.0.beta
Summary: Easy integration of lamson in django projects
Home-page: https://github.com/vvangelovski/django-lamson
Author: Vasil Vangelovski
Author-email: vvangelovski@gmail.com
License: New BSD License (http://www.opensource.org/licenses/bsd-license.php)
Download-URL: https://github.com/vvangelovski/django-lamson
Platform: UNKNOWN
Classifier: Development Status :: 4 - Beta
Classifier: Environment :: Plugins
Classifier: Framework :: Django
Classifier: Intended Audience :: Developers
Classifier: License :: OSI Approved :: BSD License
Classifier: Topic :: Software Development :: Libraries :: Python Modules
